stopwords_plus/__init__.py
stopwords_plus/cli.py
stopwords_plus/loader.py
stopwords_plus/data/en.txt
stopwords_plus/data/slang.txt
stopwords_plus/data/social.txt
stopwords_plus-0.1.0.dist-info/licenses/LICENSE
stopwords_plus-0.1.0.dist-info/METADATA
stopwords_plus-0.1.0.dist-info/WHEEL
stopwords_plus-0.1.0.dist-info/entry_points.txt
stopwords_plus-0.1.0.dist-info/top_level.txt
stopwords_plus-0.1.0.dist-info/RECORD
