Metadata-Version: 2.4
Name: stopwords-plus
Version: 0.1.0
Summary: Stopwords for 20+ languages + modern slang + social media tokens.
Author-email: Your Name <you@example.com>
License: MIT
Requires-Python: >=3.8
License-File: LICENSE
Dynamic: license-file
